chart_sos/LICENSE
chart_sos/__init__.py
chart_sos/experiments.py
chart_sos/gas_sg_0.6_108F.csv
chart_sos/gas_sg_0.6_144F.csv
chart_sos/gas_sg_0.6_19F.csv
chart_sos/gas_sg_0.6_215F.csv
chart_sos/gas_sg_0.6_250F.csv
chart_sos/gas_sg_0.6_321F.csv
chart_sos/gas_sg_0.6_37F.csv
chart_sos/gas_sg_0.6_390F.csv
chart_sos/gas_sg_0.6_55F.csv
chart_sos/gas_sg_0.6_73F.csv
chart_sos/gas_sg_0.8_102F.csv
chart_sos/gas_sg_0.8_123F.csv
chart_sos/gas_sg_0.8_144F.csv
chart_sos/gas_sg_0.8_165F.csv
chart_sos/gas_sg_0.8_206F.csv
chart_sos/gas_sg_0.8_248F.csv
chart_sos/gas_sg_0.8_331F.csv
chart_sos/gas_sg_0.8_373F.csv
chart_sos/gas_sg_0.8_40F.csv
chart_sos/gas_sg_0.8_456F.csv
chart_sos/gas_sg_0.8_60F.csv
chart_sos/gas_sg_0.8_81F.csv
chart_sos/gas_sg_1.0_113F.csv
chart_sos/gas_sg_1.0_137F.csv
chart_sos/gas_sg_1.0_161F.csv
chart_sos/gas_sg_1.0_185F.csv
chart_sos/gas_sg_1.0_209F.csv
chart_sos/gas_sg_1.0_233F.csv
chart_sos/gas_sg_1.0_257F.csv
chart_sos/gas_sg_1.0_305F.csv
chart_sos/gas_sg_1.0_352F.csv
chart_sos/gas_sg_1.0_448F.csv
chart_sos/gas_sg_1.0_66F.csv
chart_sos/gas_sg_1.0_90F.csv
chart_sos/gas_sg_1.2_134F.csv
chart_sos/gas_sg_1.2_161F.csv
chart_sos/gas_sg_1.2_188F.csv
chart_sos/gas_sg_1.2_242F.csv
chart_sos/gas_sg_1.2_269F.csv
chart_sos/gas_sg_1.2_296F.csv
chart_sos/gas_sg_1.2_323F.csv
chart_sos/gas_sg_1.2_350F.csv
chart_sos/gas_sg_1.2_404F.csv
chart_sos/py.typed
chart_sos/sos.py
chart_sos/tests.py
chart_sos-0.0.3.dist-info/LICENSE
chart_sos-0.0.3.dist-info/METADATA
chart_sos-0.0.3.dist-info/WHEEL
chart_sos-0.0.3.dist-info/top_level.txt
chart_sos-0.0.3.dist-info/RECORD
