Metadata-Version: 2.1
Name: chart_sos
Version: 0.0.3
Summary: Speed of Sound interpolation from Echometer company chart.
Home-page: https://gitlab.com/appsware/chart_sos
Author: Sarit Ritwirune
Classifier: Development Status :: 4 - Beta
Classifier: Environment :: Console
Classifier: Intended Audience :: Developers
Requires-Python: >=3.0
License-File: LICENSE
